{"train/loss/object/loss_heatmap": 0.6817300996184349, "train/loss/object/layer_-1_loss_cls": 0.26109293282032014, "train/loss/object/layer_-1_loss_bbox": 1.2178874945640563, "train/stats/object/matched_ious": 0.3532798632979393, "train/loss": 2.160710526704788, "train/grad_norm": 10.0641583442688, "learning_rate": 6.855279266916229e-07, "momentum": 0.9, "_timestamp": 1664865156.596681, "_runtime": 2969.1887152194977, "_step": 3889, "val/object/car_ap_dist_0.5": 0.2142, "val/object/car_ap_dist_1.0": 0.3607, "val/object/car_ap_dist_2.0": 0.4704, "val/object/car_ap_dist_4.0": 0.5356, "val/object/car_trans_err": 0.4411, "val/object/car_scale_err": 0.2666, "val/object/car_orient_err": 1.2035, "val/object/car_vel_err": 0.3202, "val/object/car_attr_err": 0.1394, "val/object/mATE": 0.8604, "val/object/mASE": 0.7515, "val/object/mAOE": 1.1232, "val/object/mAVE": 0.7629, "val/object/mAAE": 0.6352, "val/object/truck_ap_dist_0.5": 0.0, "val/object/truck_ap_dist_1.0": 0.0027, "val/object/truck_ap_dist_2.0": 0.009, "val/object/truck_ap_dist_4.0": 0.0096, "val/object/truck_trans_err": 0.6007, "val/object/truck_scale_err": 0.3698, "val/object/truck_orient_err": 0.8784, "val/object/truck_vel_err": 0.6815, "val/object/truck_attr_err": 0.0903, "val/object/construction_vehicle_ap_dist_0.5": 0.0, "val/object/construction_vehicle_ap_dist_1.0": 0.0, "val/object/construction_vehicle_ap_dist_2.0": 0.0, "val/object/construction_vehicle_ap_dist_4.0": 0.0, "val/object/construction_vehicle_trans_err": 1.0, "val/object/construction_vehicle_scale_err": 1.0, "val/object/construction_vehicle_orient_err": 1.0, "val/object/construction_vehicle_vel_err": 1.0, "val/object/construction_vehicle_attr_err": 1.0, "val/object/bus_ap_dist_0.5": 0.0, "val/object/bus_ap_dist_1.0": 0.0, "val/object/bus_ap_dist_2.0": 0.0, "val/object/bus_ap_dist_4.0": 0.0, "val/object/bus_trans_err": 1.0, "val/object/bus_scale_err": 1.0, "val/object/bus_orient_err": 1.0, "val/object/bus_vel_err": 1.0, "val/object/bus_attr_err": 1.0, "val/object/trailer_ap_dist_0.5": 0.0, "val/object/trailer_ap_dist_1.0": 0.0, "val/object/trailer_ap_dist_2.0": 0.0, "val/object/trailer_ap_dist_4.0": 0.0, "val/object/trailer_trans_err": 1.0, "val/object/trailer_scale_err": 1.0, "val/object/trailer_orient_err": 1.0, "val/object/trailer_vel_err": 1.0, "val/object/trailer_attr_err": 1.0, "val/object/barrier_ap_dist_0.5": 0.0, "val/object/barrier_ap_dist_1.0": 0.0, "val/object/barrier_ap_dist_2.0": 0.0, "val/object/barrier_ap_dist_4.0": 0.0, "val/object/barrier_trans_err": 1.0, "val/object/barrier_scale_err": 1.0, "val/object/barrier_orient_err": 1.0, "val/object/barrier_vel_err": NaN, "val/object/barrier_attr_err": NaN, "val/object/motorcycle_ap_dist_0.5": 0.0, "val/object/motorcycle_ap_dist_1.0": 0.0, "val/object/motorcycle_ap_dist_2.0": 0.0, "val/object/motorcycle_ap_dist_4.0": 0.0, "val/object/motorcycle_trans_err": 0.8469, "val/object/motorcycle_scale_err": 0.7118, "val/object/motorcycle_orient_err": 1.5512, "val/object/motorcycle_vel_err": 0.1018, "val/object/motorcycle_attr_err": 0.0, "val/object/bicycle_ap_dist_0.5": 0.0, "val/object/bicycle_ap_dist_1.0": 0.0, "val/object/bicycle_ap_dist_2.0": 0.0, "val/object/bicycle_ap_dist_4.0": 0.0, "val/object/bicycle_trans_err": 1.0, "val/object/bicycle_scale_err": 1.0, "val/object/bicycle_orient_err": 1.0, "val/object/bicycle_vel_err": 1.0, "val/object/bicycle_attr_err": 1.0, "val/object/pedestrian_ap_dist_0.5": 0.1916, "val/object/pedestrian_ap_dist_1.0": 0.2372, "val/object/pedestrian_ap_dist_2.0": 0.2608, "val/object/pedestrian_ap_dist_4.0": 0.2987, "val/object/pedestrian_trans_err": 0.4736, "val/object/pedestrian_scale_err": 0.3934, "val/object/pedestrian_orient_err": 1.476, "val/object/pedestrian_vel_err": 1.0, "val/object/pedestrian_attr_err": 0.852, "val/object/traffic_cone_ap_dist_0.5": 0.0, "val/object/traffic_cone_ap_dist_1.0": 0.0, "val/object/traffic_cone_ap_dist_2.0": 0.0, "val/object/traffic_cone_ap_dist_4.0": 0.0, "val/object/traffic_cone_trans_err": 1.2417, "val/object/traffic_cone_scale_err": 0.7733, "val/object/traffic_cone_orient_err": NaN, "val/object/traffic_cone_vel_err": NaN, "val/object/traffic_cone_attr_err": NaN, "val/object/nds": 0.13137957993672944, "val/object/map": 0.06476378629978842, "_wandb": {"runtime": 2969}}