{"train/loss/object/loss_cont": 2.9993247985839844, "train/loss/object/loss_heatmap": 0.9737098014354706, "train/loss/object/layer_-1_loss_cls": 0.4332448357343674, "train/loss/object/layer_-1_loss_bbox": 1.4168797504901887, "train/stats/object/matched_ious": 0.2865352895855904, "train/loss": 5.823159217834473, "train/grad_norm": 14.921835308074952, "learning_rate": 6.855279266916229e-07, "momentum": 0.9, "_timestamp": 1664892276.4264975, "_runtime": 2113.779272556305, "_step": 1945, "val/object/car_ap_dist_0.5": 0.1669, "val/object/car_ap_dist_1.0": 0.313, "val/object/car_ap_dist_2.0": 0.4391, "val/object/car_ap_dist_4.0": 0.4993, "val/object/car_trans_err": 0.5004, "val/object/car_scale_err": 0.2895, "val/object/car_orient_err": 1.3145, "val/object/car_vel_err": 0.4787, "val/object/car_attr_err": 0.1926, "val/object/mATE": 0.8422, "val/object/mASE": 0.7318, "val/object/mAOE": 1.2278, "val/object/mAVE": 1.3134, "val/object/mAAE": 0.5974, "val/object/truck_ap_dist_0.5": 0.0, "val/object/truck_ap_dist_1.0": 0.0015, "val/object/truck_ap_dist_2.0": 0.0018, "val/object/truck_ap_dist_4.0": 0.0018, "val/object/truck_trans_err": 0.6895, "val/object/truck_scale_err": 0.3499, "val/object/truck_orient_err": 1.2576, "val/object/truck_vel_err": 0.3851, "val/object/truck_attr_err": 0.0438, "val/object/construction_vehicle_ap_dist_0.5": 0.0, "val/object/construction_vehicle_ap_dist_1.0": 0.0, "val/object/construction_vehicle_ap_dist_2.0": 0.0, "val/object/construction_vehicle_ap_dist_4.0": 0.0, "val/object/construction_vehicle_trans_err": 1.0, "val/object/construction_vehicle_scale_err": 1.0, "val/object/construction_vehicle_orient_err": 1.0, "val/object/construction_vehicle_vel_err": 1.0, "val/object/construction_vehicle_attr_err": 1.0, "val/object/bus_ap_dist_0.5": 0.0, "val/object/bus_ap_dist_1.0": 0.0, "val/object/bus_ap_dist_2.0": 0.0, "val/object/bus_ap_dist_4.0": 0.0, "val/object/bus_trans_err": 1.0, "val/object/bus_scale_err": 1.0, "val/object/bus_orient_err": 1.0, "val/object/bus_vel_err": 1.0, "val/object/bus_attr_err": 1.0, "val/object/trailer_ap_dist_0.5": 0.0, "val/object/trailer_ap_dist_1.0": 0.0, "val/object/trailer_ap_dist_2.0": 0.0, "val/object/trailer_ap_dist_4.0": 0.0, "val/object/trailer_trans_err": 1.0, "val/object/trailer_scale_err": 1.0, "val/object/trailer_orient_err": 1.0, "val/object/trailer_vel_err": 1.0, "val/object/trailer_attr_err": 1.0, "val/object/barrier_ap_dist_0.5": 0.0, "val/object/barrier_ap_dist_1.0": 0.0, "val/object/barrier_ap_dist_2.0": 0.0, "val/object/barrier_ap_dist_4.0": 0.0, "val/object/barrier_trans_err": 1.0, "val/object/barrier_scale_err": 1.0, "val/object/barrier_orient_err": 1.0, "val/object/barrier_vel_err": NaN, "val/object/barrier_attr_err": NaN, "val/object/motorcycle_ap_dist_0.5": 0.0, "val/object/motorcycle_ap_dist_1.0": 0.0, "val/object/motorcycle_ap_dist_2.0": 0.0, "val/object/motorcycle_ap_dist_4.0": 0.001, "val/object/motorcycle_trans_err": 0.9, "val/object/motorcycle_scale_err": 0.7546, "val/object/motorcycle_orient_err": 1.6135, "val/object/motorcycle_vel_err": 0.117, "val/object/motorcycle_attr_err": 0.0, "val/object/bicycle_ap_dist_0.5": 0.0, "val/object/bicycle_ap_dist_1.0": 0.0, "val/object/bicycle_ap_dist_2.0": 0.0, "val/object/bicycle_ap_dist_4.0": 0.0, "val/object/bicycle_trans_err": 0.6349, "val/object/bicycle_scale_err": 0.8207, "val/object/bicycle_orient_err": 1.2682, "val/object/bicycle_vel_err": 5.521, "val/object/bicycle_attr_err": 0.6727, "val/object/pedestrian_ap_dist_0.5": 0.2463, "val/object/pedestrian_ap_dist_1.0": 0.3156, "val/object/pedestrian_ap_dist_2.0": 0.3516, "val/object/pedestrian_ap_dist_4.0": 0.3959, "val/object/pedestrian_trans_err": 0.4808, "val/object/pedestrian_scale_err": 0.3514, "val/object/pedestrian_orient_err": 1.596, "val/object/pedestrian_vel_err": 1.0058, "val/object/pedestrian_attr_err": 0.8703, "val/object/traffic_cone_ap_dist_0.5": 0.0, "val/object/traffic_cone_ap_dist_1.0": 0.0, "val/object/traffic_cone_ap_dist_2.0": 0.0, "val/object/traffic_cone_ap_dist_4.0": 0.0, "val/object/traffic_cone_trans_err": 1.2163, "val/object/traffic_cone_scale_err": 0.752, "val/object/traffic_cone_orient_err": NaN, "val/object/traffic_cone_vel_err": NaN, "val/object/traffic_cone_attr_err": NaN, "val/object/nds": 0.11703613770528498, "val/object/map": 0.06835429565340659, "_wandb": {"runtime": 2114}}