{"train/loss/object/loss_cont": 6.008571128845215, "train/loss/object/loss_heatmap": 1.6461396288871766, "train/loss/object/layer_-1_loss_cls": 0.7584275615215301, "train/loss/object/layer_-1_loss_bbox": 1.889104585647583, "train/stats/object/matched_ious": 0.2139457270503044, "train/loss": 10.302242908477783, "train/grad_norm": 13.969258098602294, "learning_rate": 8.536998372026805e-05, "momentum": 0.9, "_timestamp": 1664816997.9294405, "_runtime": 899.2917404174805, "_step": 910, "val/object/car_ap_dist_0.5": 0.0064, "val/object/car_ap_dist_1.0": 0.0737, "val/object/car_ap_dist_2.0": 0.2061, "val/object/car_ap_dist_4.0": 0.276, "val/object/car_trans_err": 0.7751, "val/object/car_scale_err": 0.4115, "val/object/car_orient_err": 1.3439, "val/object/car_vel_err": 0.4631, "val/object/car_attr_err": 0.2001, "val/object/mATE": 0.9339, "val/object/mASE": 0.8972, "val/object/mAOE": 1.1076, "val/object/mAVE": 0.9484, "val/object/mAAE": 0.8934, "val/object/truck_ap_dist_0.5": 0.0, "val/object/truck_ap_dist_1.0": 0.0, "val/object/truck_ap_dist_2.0": 0.0, "val/object/truck_ap_dist_4.0": 0.0, "val/object/truck_trans_err": 1.0, "val/object/truck_scale_err": 1.0, "val/object/truck_orient_err": 1.0, "val/object/truck_vel_err": 1.0, "val/object/truck_attr_err": 1.0, "val/object/construction_vehicle_ap_dist_0.5": 0.0, "val/object/construction_vehicle_ap_dist_1.0": 0.0, "val/object/construction_vehicle_ap_dist_2.0": 0.0, "val/object/construction_vehicle_ap_dist_4.0": 0.0, "val/object/construction_vehicle_trans_err": 1.0, "val/object/construction_vehicle_scale_err": 1.0, "val/object/construction_vehicle_orient_err": 1.0, "val/object/construction_vehicle_vel_err": 1.0, "val/object/construction_vehicle_attr_err": 1.0, "val/object/bus_ap_dist_0.5": 0.0, "val/object/bus_ap_dist_1.0": 0.0, "val/object/bus_ap_dist_2.0": 0.0, "val/object/bus_ap_dist_4.0": 0.0, "val/object/bus_trans_err": 1.0, "val/object/bus_scale_err": 1.0, "val/object/bus_orient_err": 1.0, "val/object/bus_vel_err": 1.0, "val/object/bus_attr_err": 1.0, "val/object/trailer_ap_dist_0.5": 0.0, "val/object/trailer_ap_dist_1.0": 0.0, "val/object/trailer_ap_dist_2.0": 0.0, "val/object/trailer_ap_dist_4.0": 0.0, "val/object/trailer_trans_err": 1.0, "val/object/trailer_scale_err": 1.0, "val/object/trailer_orient_err": 1.0, "val/object/trailer_vel_err": 1.0, "val/object/trailer_attr_err": 1.0, "val/object/barrier_ap_dist_0.5": 0.0, "val/object/barrier_ap_dist_1.0": 0.0, "val/object/barrier_ap_dist_2.0": 0.0, "val/object/barrier_ap_dist_4.0": 0.0, "val/object/barrier_trans_err": 1.0, "val/object/barrier_scale_err": 1.0, "val/object/barrier_orient_err": 1.0, "val/object/barrier_vel_err": NaN, "val/object/barrier_attr_err": NaN, "val/object/motorcycle_ap_dist_0.5": 0.0, "val/object/motorcycle_ap_dist_1.0": 0.0, "val/object/motorcycle_ap_dist_2.0": 0.0, "val/object/motorcycle_ap_dist_4.0": 0.0, "val/object/motorcycle_trans_err": 1.0, "val/object/motorcycle_scale_err": 1.0, "val/object/motorcycle_orient_err": 1.0, "val/object/motorcycle_vel_err": 1.0, "val/object/motorcycle_attr_err": 1.0, "val/object/bicycle_ap_dist_0.5": 0.0, "val/object/bicycle_ap_dist_1.0": 0.0, "val/object/bicycle_ap_dist_2.0": 0.0, "val/object/bicycle_ap_dist_4.0": 0.0, "val/object/bicycle_trans_err": 1.0, "val/object/bicycle_scale_err": 1.0, "val/object/bicycle_orient_err": 1.0, "val/object/bicycle_vel_err": 1.0, "val/object/bicycle_attr_err": 1.0, "val/object/pedestrian_ap_dist_0.5": 0.0, "val/object/pedestrian_ap_dist_1.0": 0.0084, "val/object/pedestrian_ap_dist_2.0": 0.0159, "val/object/pedestrian_ap_dist_4.0": 0.0291, "val/object/pedestrian_trans_err": 0.5644, "val/object/pedestrian_scale_err": 0.5608, "val/object/pedestrian_orient_err": 1.6244, "val/object/pedestrian_vel_err": 1.1244, "val/object/pedestrian_attr_err": 0.9467, "val/object/traffic_cone_ap_dist_0.5": 0.0, "val/object/traffic_cone_ap_dist_1.0": 0.0, "val/object/traffic_cone_ap_dist_2.0": 0.0, "val/object/traffic_cone_ap_dist_4.0": 0.0, "val/object/traffic_cone_trans_err": 1.0, "val/object/traffic_cone_scale_err": 1.0, "val/object/traffic_cone_orient_err": NaN, "val/object/traffic_cone_vel_err": NaN, "val/object/traffic_cone_attr_err": NaN, "val/object/nds": 0.040398781860361235, "val/object/map": 0.015392074914925483}